pypistudy_auspiciouschan/__init__.py
pypistudy_auspiciouschan/main.py
pypistudy_auspiciouschan-0.0.1.dist-info/METADATA
pypistudy_auspiciouschan-0.0.1.dist-info/WHEEL
pypistudy_auspiciouschan-0.0.1.dist-info/licenses/LICENSE
pypistudy_auspiciouschan-0.0.1.dist-info/RECORD
