Metadata-Version: 2.1
Name: pypistudy_auspiciouschan
Version: 0.0.1
Summary: PyPi Study
Project-URL: Homepage, https://gitee.com/AuspiciousChan/py-pi-study
Project-URL: Issues, https://gitee.com/AuspiciousChan/py-pi-study/issues
Author-email: Auspicious Chan <AuspicioiusChanWork@gmail.com>
License-File: LICENSE
Classifier: License :: OSI Approved :: MIT License
Classifier: Operating System :: OS Independent
Classifier: Programming Language :: Python :: 3
Requires-Python: >=3.10
